Verilog/Sequential Logic/D_ff/mod.v
module dff(
    input clk,
    input reset,
    input d,
    output reg q
);
    always @(posedge clk) begin
        if (reset)
            q <= 0;
        else
            q <= d;
    end
endmodule

Verilog/Sequential Logic/D_ff/test.v
module testbench;
    reg clk, reset, d;
    wire q;

    dff uut(.clk(clk), .reset(reset), .d(d), .q(q));

    initial clk = 0;
    always #5 clk = ~clk;

    initial begin
        $dumpfile("wave.vcd");
        $dumpvars(0, testbench);
        $monitor("time=%0t clk=%b reset=%b d=%b q=%b", $time, clk, reset, d, q);

        reset = 1; d = 0; #12;
        reset = 0; d = 1; #10;
        d = 0; #10;
        d = 1; #2;
        d = 0; #8;
        d = 1; #10;

        $finish;
    end
endmodule

Verilog/Sequential Logic/D_ff/wave.vcd
$date
	Fri Oct 09 16:58:25 2026
$end
$version
	Icarus Verilog
$end
$timescale
	1s
$end
$scope module testbench $end
$var wire 1 ! q $end
$var reg 1 " clk $end
$var reg 1 # d $end
$var reg 1 $ reset $end
$scope module uut $end
$var wire 1 " clk $end
$var wire 1 # d $end
$var wire 1 $ reset $end
$var reg 1 ! q $end
$upscope $end
$upscope $end
$enddefinitions $end
$comment Show the parameter values. $end
$dumpall
$end
#0
$dumpvars
1$
0#
0"
x!
$end
#5
0!
1"
#10
0"
#12
1#
0$
#15
1!
1"
#20
0"
#22
0#
#25
0!
1"
#30
0"
#32
1#
#34
0#
#35
1"
#40
0"
#42
1#
#45
1!
1"
