Verilog/Sequential Logic/4_bitcount/mod.v
module counter4(
    input clk,
    input reset,
    input en,
    output reg [3:0] count
);
    always @(posedge clk) begin
        if (reset)
            count <= 0;
        else if (en)
            count <= count + 1;
    end
endmodule

Verilog/Sequential Logic/4_bitcount/test.v
module testbench;
    reg clk, reset, en;
    wire [3:0] count;

    counter4 uut(.clk(clk), .reset(reset), .en(en), .count(count));

    initial clk = 0;
    always #5 clk = ~clk;

    initial begin
        $dumpfile("wave.vcd");
        $dumpvars(0, testbench);
        $monitor("time=%0t reset=%b en=%b count=%d", $time, reset, en, count);

        reset = 1; en = 0; #12;
        reset = 0; en = 1; #165;
        en = 0; #30;
        reset = 1; #10;

        $finish;
    end
endmodule

Verilog/Sequential Logic/4_bitcount/wave.vcd
$date
	Fri Oct 09 20:34:10 2026
$end
$version
	Icarus Verilog
$end
$timescale
	1s
$end
$scope module testbench $end
$var wire 4 ! count [3:0] $end
$var reg 1 " clk $end
$var reg 1 # en $end
$var reg 1 $ reset $end
$scope module uut $end
$var wire 1 " clk $end
$var wire 1 # en $end
$var wire 1 $ reset $end
$var reg 4 % count [3:0] $end
$upscope $end
$upscope $end
$enddefinitions $end
$comment Show the parameter values. $end
$dumpall
$end
#0
$dumpvars
bx %
1$
0#
0"
bx !
$end
#5
b0 !
b0 %
1"
#10
0"
#12
1#
0$
#15
b1 !
b1 %
1"
#20
0"
#25
b10 !
b10 %
1"
#30
0"
#35
b11 !
b11 %
1"
#40
0"
#45
b100 !
b100 %
1"
#50
0"
#55
b101 !
b101 %
1"
#60
0"
#65
b110 !
b110 %
1"
#70
0"
#75
b111 !
b111 %
1"
#80
0"
#85
b1000 !
b1000 %
1"
#90
0"
#95
b1001 !
b1001 %
1"
#100
0"
#105
b1010 !
b1010 %
1"
#110
0"
#115
b1011 !
b1011 %
1"
#120
0"
#125
b1100 !
b1100 %
1"
#130
0"
#135
b1101 !
b1101 %
1"
#140
0"
#145
b1110 !
b1110 %
1"
#150
0"
#155
b1111 !
b1111 %
1"
#160
0"
#165
b0 !
b0 %
1"
#170
0"
#175
b1 !
b1 %
1"
#177
0#
#180
0"
#185
1"
#190
0"
#195
1"
#200
0"
#205
1"
#207
1$
#210
0"
#215
b0 !
b0 %
1"
