Verilog/Sequential Logic/4_bitreg/mod.v
module reg4(
    input clk,
    input reset,
    input en,
    input [3:0] d,
    output reg [3:0]q
);
    always @(posedge clk) begin
        if (reset)
            q <= 0;
        else if (en)
            q <= d;
    end
endmodule

Verilog/Sequential Logic/4_bitreg/test.v
module testbench;
    reg clk, reset, en;
    reg [3:0] d;
    wire [3:0] q;

    reg4 uut(.clk(clk), .reset(reset), .en(en), .d(d), .q(q));

    initial clk = 0;
    always #5 clk = ~clk;

    initial begin
        $dumpfile("wave.vcd");
        $dumpvars(0, testbench);
        $monitor("time=%0t reset=%b en=%b d=%d q=%d", $time, reset, en, d, q);

        reset = 1; en = 0; d = 4'd0; #12;
        reset = 0; en = 1; d = 4'd9; #10;
        d = 4'd5; en = 0; #10;
        d = 4'd12; #10;
        en = 1; #10;
        reset = 1; #10;

        $finish;
    end
endmodule

Verilog/Sequential Logic/4_bitreg/wave.vcd
$date
	Fri Oct 09 17:01:53 2026
$end
$version
	Icarus Verilog
$end
$timescale
	1s
$end
$scope module testbench $end
$var wire 4 ! q [3:0] $end
$var reg 1 " clk $end
$var reg 4 # d [3:0] $end
$var reg 1 $ en $end
$var reg 1 % reset $end
$scope module uut $end
$var wire 1 " clk $end
$var wire 4 & d [3:0] $end
$var wire 1 $ en $end
$var wire 1 % reset $end
$var reg 4 ' q [3:0] $end
$upscope $end
$upscope $end
$enddefinitions $end
$comment Show the parameter values. $end
$dumpall
$end
#0
$dumpvars
bx '
b0 &
1%
0$
b0 #
0"
bx !
$end
#5
b0 !
b0 '
1"
#10
0"
#12
b1001 #
b1001 &
1$
0%
#15
b1001 !
b1001 '
1"
#20
0"
#22
0$
b101 #
b101 &
#25
1"
#30
0"
#32
b1100 #
b1100 &
#35
1"
#40
0"
#42
1$
#45
b1100 !
b1100 '
1"
#50
0"
#52
1%
#55
b0 !
b0 '
1"
