Verilog/ALU/module.v
module alu_4(
    input [3:0] a,
    input [3:0] b,
    input [1:0] sel,
    output reg [3:0] result
);
    always @(*) begin
        case (sel)
            2'b00: result = a + b;
            2'b01: result = a - b;
            2'b10: result = a & b;
            2'b11: result = a | b;
        endcase
    end
endmodule

Verilog/Combinational Logic/ALU/testbench.v
module testbench;
    reg [3:0] a, b;
    reg [1:0] sel;
    wire [3:0] result;

    alu_4 uut(.a(a), .b(b), .sel(sel), .result(result));

    initial begin
        $dumpfile("wave.vcd");
        $dumpvars(0, testbench);
        $monitor("time=%0t a=%d b=%d sel=%b result=%d", $time, a, b, sel, result);

        a = 4'd9; b = 4'd5;
        sel = 2'b00; #10;
        sel = 2'b01; #10;
        sel = 2'b10; #10;
        sel = 2'b11; #10;

        a = 4'd3; b = 4'd7;
        sel = 2'b00; #10;
        sel = 2'b01; #10;
        sel = 2'b10; #10;
        sel = 2'b11; #10;

        $finish;
    end
endmodule

Verilog/ALU/wave.vcd
$date
	Fri Oct 09 10:41:55 2026
$end
$version
	Icarus Verilog
$end
$timescale
	1s
$end
$scope module testbench $end
$var wire 4 ! result [3:0] $end
$var reg 4 " a [3:0] $end
$var reg 4 # b [3:0] $end
$var reg 2 $ sel [1:0] $end
$scope module uut $end
$var wire 4 % a [3:0] $end
$var wire 4 & b [3:0] $end
$var wire 2 ' sel [1:0] $end
$var reg 4 ( result [3:0] $end
$upscope $end
$upscope $end
$enddefinitions $end
$comment Show the parameter values. $end
$dumpall
$end
#0
$dumpvars
b1110 (
b0 '
b101 &
b1001 %
b0 $
b101 #
b1001 "
b1110 !
$end
#10
b100 !
b100 (
b1 $
b1 '
#20
b1 !
b1 (
b10 $
b10 '
#30
b1101 !
b1101 (
b11 $
b11 '
#40
b1010 !
b1010 (
b0 $
b0 '
b111 #
b111 &
b11 "
b11 %
#50
b1100 !
b1100 (
b1 $
b1 '
#60
b11 !
b11 (
b10 $
b10 '
#70
b111 !
b111 (
b11 $
b11 '
